virtualdojo/__init__.py
virtualdojo/__main__.py
virtualdojo/cli.py
virtualdojo/client.py
virtualdojo/config.py
virtualdojo/exceptions.py
virtualdojo/commands/__init__.py
virtualdojo/commands/ai.py
virtualdojo/commands/auth.py
virtualdojo/commands/config.py
virtualdojo/commands/files.py
virtualdojo/commands/logs.py
virtualdojo/commands/records.py
virtualdojo/commands/schema.py
virtualdojo/commands/sql.py
virtualdojo/commands/system.py
virtualdojo/models/__init__.py
virtualdojo/models/auth.py
virtualdojo/models/records.py
virtualdojo/utils/__init__.py
virtualdojo/utils/filters.py
virtualdojo/utils/output.py
virtualdojo/utils/version_check.py
virtualdojo-0.6.3.dist-info/METADATA
virtualdojo-0.6.3.dist-info/WHEEL
virtualdojo-0.6.3.dist-info/entry_points.txt
virtualdojo-0.6.3.dist-info/licenses/LICENSE
virtualdojo-0.6.3.dist-info/RECORD
